dimlpfidex/dimlp.cp310-win_amd64.pyd
dimlpfidex/fidex.cp310-win_amd64.pyd
trainings/__init__.py
trainings/cnnTrn.py
trainings/computeRocCurve.py
trainings/gradBoostTrn.py
trainings/mlpTrn.py
trainings/normalization.py
trainings/parameters.py
trainings/randForestsTrn.py
trainings/stairObj.py
trainings/svmTrn.py
trainings/templates/config_cnn.json
trainings/templates/config_cnnTrn.json
trainings/templates/config_gradBoost.json
trainings/templates/config_mlp.json
trainings/templates/config_normalization.json
trainings/templates/config_randForests.json
trainings/templates/config_roc.json
trainings/templates/config_svm.json
trainings/trnFun.py
dimlpfidex-1.0.1.dist-info/METADATA
dimlpfidex-1.0.1.dist-info/WHEEL
dimlpfidex-1.0.1.dist-info/licenses/LICENSE
dimlpfidex-1.0.1.dist-info/RECORD
