Metadata-Version: 2.1
Name: dimlpfidex
Version: 1.0.1
Summary: Discretized Interpretable Multi Layer Perceptron (DIMLP) and related algorithms
Keywords: machine learning,xai
Author-Email: Jean-Marc Boutay <jean-marc.boutay@hesge.ch>, Damian Boquete Costa <damian.boquete-costa@hesge.ch>, Guido Bologna <guido.bologna@hesge.ch>
License: BSD License (BSD-3-Clause)
Classifier: Operating System :: Microsoft :: Windows
Classifier: Operating System :: POSIX
Classifier: Operating System :: Unix
Classifier: Operating System :: MacOS
Classifier: Intended Audience :: Developers
Classifier: Intended Audience :: Education
Classifier: Intended Audience :: Science/Research
Classifier: License :: OSI Approved :: BSD License
Classifier: Topic :: Scientific/Engineering
Classifier: Topic :: Scientific/Engineering :: Mathematics
Classifier: Topic :: Scientific/Engineering :: Artificial Intelligence
Classifier: Topic :: Software Development
Classifier: Topic :: Software Development :: Libraries
Classifier: Topic :: Software Development :: Libraries :: Python Modules
Classifier: Programming Language :: C++
Classifier: Programming Language :: Python :: 3
Requires-Python: >=3.9.0
Requires-Dist: pybind11>=2.12.0
Requires-Dist: pybind11-global>=2.10.4
Requires-Dist: numpy<2.0
Requires-Dist: scikit-learn>=1.1.3
Requires-Dist: keras>=3.3
Requires-Dist: torch>=2.3
Requires-Dist: torchvision>=0.18
Requires-Dist: matplotlib>=3.7.4
Requires-Dist: build>=1.0.3
Requires-Dist: cibuildwheel>=2.19.1
Requires-Dist: breathe>=4.35.0
Requires-Dist: exhale>=0.3.7
Requires-Dist: sphinx>=7.3.7
Requires-Dist: sphinx-rtd-theme>=2.0.0
